pcse_gym/__init__.py
pcse_gym/envs/__init__.py
pcse_gym/envs/common_env.py
pcse_gym/envs/configs/Lintul3.conf
pcse_gym/envs/configs/Wofost81_NWLP_FD.conf
pcse_gym/envs/configs/agro/agromanagement_fertilization.yaml
pcse_gym/envs/configs/agro/potato_cropcalendar.yaml
pcse_gym/envs/configs/agro/sugarbeet_calendar.yaml
pcse_gym/envs/configs/agro/wheat_cropcalendar.yaml
pcse_gym/envs/configs/crop/SUG0601.CAB
pcse_gym/envs/configs/crop/YAMLCropDataProvider.pkl
pcse_gym/envs/configs/crop/crops.yaml
pcse_gym/envs/configs/crop/lintul3_winterwheat.crop
pcse_gym/envs/configs/crop/wheat.yaml
pcse_gym/envs/configs/site/lintul3_springwheat.site
pcse_gym/envs/configs/soil/ec1.CAB
pcse_gym/envs/configs/soil/ec2.CAB
pcse_gym/envs/configs/soil/ec3.CAB
pcse_gym/envs/configs/soil/ec4.CAB
pcse_gym/envs/configs/soil/lintul3_springwheat.soil
pcse_gym/envs/rewards.py
pcse_gym/envs/sb3.py
pcse_gym/envs/winterwheat.py
pcse_gym/utils/__init__.py
pcse_gym/utils/defaults.py
pcse_gym/utils/eval.py
pcse_gym/utils/process_pcse_output.py
cropgym-0.0.1.dist-info/LICENSE
cropgym-0.0.1.dist-info/METADATA
cropgym-0.0.1.dist-info/WHEEL
cropgym-0.0.1.dist-info/RECORD
